python_vtk/__init__.py
python_vtk/io.py
python_vtk/models.py
python_vtk-0.1.0.dist-info/WHEEL
python_vtk-0.1.0.dist-info/METADATA
python_vtk-0.1.0.dist-info/RECORD
